{
  "trend_lineage":[
    {
      "trend_checksum":"33bbc0557d10e04faf86625f741372c593c4f51dfea660863301232a4ed329b0",
      "trend_direction":"STABLE",
      "trend_key":"alert_volume",
      "trend_type":"ALERT_VOLUME"
    },
    {
      "trend_checksum":"2b97258245952aaffa4f739bd77c02ddb7d1196ed002143f21f78f5d953e43eb",
      "trend_direction":"STABLE",
      "trend_key":"batch_growth",
      "trend_type":"BATCH_GROWTH"
    },
    {
      "trend_checksum":"0b90f4c7f7b750548ff621fab3dba9d69de118cf65a4edced39fc5b225e3fec6",
      "trend_direction":"STABLE",
      "trend_key":"failure_rate",
      "trend_type":"FAILURE_RATE"
    },
    {
      "trend_checksum":"320a0a5bf21bc50bcb36a3804b28915be40ac9984c326b38c2848272e34b3c67",
      "trend_direction":"STABLE",
      "trend_key":"queue_growth",
      "trend_type":"QUEUE_GROWTH"
    },
    {
      "trend_checksum":"743473a8375ee3c62b9b3c9c31121f44ca25bf14e0a8b61b55272bdf580b5e32",
      "trend_direction":"STABLE",
      "trend_key":"replay_warning_rate",
      "trend_type":"REPLAY_WARNING_RATE"
    },
    {
      "trend_checksum":"5d676b70fdefe26bcc7ba2c8dafa93d74641800944932e4f19295901eea123d4",
      "trend_direction":"STABLE",
      "trend_key":"worker_utilization",
      "trend_type":"WORKER_UTILIZATION"
    },
    {
      "trend_checksum":"4843ebf54cdc78f34e7db573c97ae7396ac000c24d2e180558aa505d4cd5b0dc",
      "trend_direction":"STABLE",
      "trend_key":"workflow_throughput",
      "trend_type":"WORKFLOW_THROUGHPUT"
    }
  ]
}